catnip_bio/__init__.py
catnip_bio-0.0.0.dist-info/LICENSE
catnip_bio-0.0.0.dist-info/METADATA
catnip_bio-0.0.0.dist-info/WHEEL
catnip_bio-0.0.0.dist-info/top_level.txt
catnip_bio-0.0.0.dist-info/RECORD
